pdo/__init__.py
pdo/exception.py
pdo/pdo.py
pdo/databases/__init__.py
pdo/databases/mysql_database.py
pdo/databases/postgresql_database.py
pdo/databases/sqlite_database.py
pdo_pip-1.1.1.dist-info/METADATA
pdo_pip-1.1.1.dist-info/WHEEL
pdo_pip-1.1.1.dist-info/top_level.txt
pdo_pip-1.1.1.dist-info/RECORD
