Metadata-Version: 2.1
Name: pdo-pip
Version: 1.1.1
Summary: An interface to access a database from Python.
Home-page: https://github.com/AlexisHuvier/PDO
Author: AlexisHuvier
Author-email: lavapower84@gmail.com
License: GNU GPLv3
Platform: UNKNOWN
Classifier: Development Status :: 5 - Production/Stable
Classifier: Operating System :: OS Independent
Classifier: Programming Language :: Python
Classifier: Programming Language :: Python :: 3
Classifier: Programming Language :: Python :: 3.7
Classifier: Intended Audience :: Developers
Classifier: Topic :: Database
